heaven_base/__init__.py
heaven_base/__init__.py.bak
heaven_base/auto_summarizing_agent.py
heaven_base/baseheavenagent.py
heaven_base/baseheaventool.py
heaven_base/decorators.py
heaven_base/documentation_pipeline.py
heaven_base/make_heaven_tool_from_docstring.py
heaven_base/mcp_tool_wrapper.py
heaven_base/unified_chat.py
heaven_base/acolyte_v2/__init__.py
heaven_base/acolyte_v2/acolyte_agent_config.py
heaven_base/acolyte_v2/run_acolyte.py
heaven_base/agents/coder_agent_config.py
heaven_base/agents/concept_resolver_agent.py
heaven_base/agents/disciple_agent_config.py
heaven_base/agents/phase_aggregator_agent.py
heaven_base/agents/phase_detector_agent.py
heaven_base/agents/prompt_engineering_agent_config.py
heaven_base/agents/redactor_agent_config.py
heaven_base/agents/scripture_writer_agent_config.py
heaven_base/agents/self_learning_agent.py
heaven_base/agents/self_learning_agent_config.py
heaven_base/agents/self_learning_agent_skeleton.py
heaven_base/agents/subphase_detector_agent.py
heaven_base/agents/decider/__init__.py
heaven_base/agents/decider/decider_agent_config.py
heaven_base/agents/docstring_agent/__init__.py
heaven_base/agents/docstring_agent/docstring_agent_config.py
heaven_base/agents/example_maker/__init__.py
heaven_base/agents/example_maker/example_maker_agent_config.py
heaven_base/agents/summary_agent/__init__.py
heaven_base/agents/summary_agent/summary_agent.py
heaven_base/agents/summary_agent/summary_util.py
heaven_base/cli/__init__.py
heaven_base/cli/heaven_cli.py
heaven_base/configs/__init__.py
heaven_base/configs/base_config.py
heaven_base/configs/hermes_config.py
heaven_base/configs/uni_api_config.json
heaven_base/docs/__init__.py
heaven_base/docs/examples/__init__.py
heaven_base/docs/examples/heaven_callbacks.py
heaven_base/langgraph/__init__.py
heaven_base/langgraph/foundation.py
heaven_base/langgraph/hermes_legos.py
heaven_base/langgraph/utility_legos.py
heaven_base/mcps/__init__.py
heaven_base/mcps/toolbox_server.py
heaven_framework-0.1.19.dist-info/licenses/LICENSE
heaven_framework-0.1.19.dist-info/METADATA
heaven_framework-0.1.19.dist-info/WHEEL
heaven_framework-0.1.19.dist-info/entry_points.txt
heaven_framework-0.1.19.dist-info/top_level.txt
heaven_framework-0.1.19.dist-info/RECORD
