Metadata-Version: 2.4
Name: heaven-framework
Version: 0.1.19
Summary: HEAVEN - Hierarchical, Embodied, Autonomously Validating Evolution Network
Home-page: https://github.com/heaven-framework/heaven
Author: HEAVEN Team
Author-email: HEAVEN Team <heaven@example.com>
License: MIT
Project-URL: Homepage, https://github.com/sancovp/heaven-framework
Project-URL: Repository, https://github.com/sancovp/heaven-framework.git
Project-URL: Documentation, https://heaven-framework.readthedocs.io
Project-URL: Issues, https://github.com/sancovp/heaven-framework/issues
Classifier: Development Status :: 3 - Alpha
Classifier: Intended Audience :: Developers
Classifier: License :: OSI Approved :: MIT License
Classifier: Programming Language :: Python :: 3
Classifier: Programming Language :: Python :: 3.9
Classifier: Programming Language :: Python :: 3.10
Classifier: Programming Language :: Python :: 3.11
Classifier: Topic :: Software Development :: Libraries :: Python Modules
Classifier: Topic :: Scientific/Engineering :: Artificial Intelligence
Requires-Python: >=3.9
License-File: LICENSE
Requires-Dist: google-adk>=0.2.0
Requires-Dist: google-genai>=1.11.0
Requires-Dist: langchain-anthropic>=0.3.13
Requires-Dist: langchain-core>=0.3.65
Requires-Dist: langchain-deepseek>=0.1.2
Requires-Dist: langchain-google-genai>=2.1.5
Requires-Dist: langchain-groq>=0.2.4
Requires-Dist: langchain-openai>=0.3.22
Requires-Dist: langchain>=0.1.0
Requires-Dist: langgraph>=0.2.0
Requires-Dist: litellm>=1.67.5
Requires-Dist: pydantic>=2.11.7
Requires-Dist: requests>=2.31.0
Requires-Dist: httpx>=0.24.0
Requires-Dist: fastmcp==2.12.2
Provides-Extra: dev
Requires-Dist: pytest>=7.0; extra == "dev"
Requires-Dist: pytest-asyncio>=0.21; extra == "dev"
Requires-Dist: black>=23.0; extra == "dev"
Requires-Dist: ruff>=0.1.0; extra == "dev"
Dynamic: author
Dynamic: home-page
Dynamic: license-file
Dynamic: requires-python
